loggerbundle/LoggerBundle.py
loggerbundle/LoggerBundleTest.py
loggerbundle/LoggerFactory.py
loggerbundle/_config/config.yaml
loggerbundle/_config/config_test.yaml
loggerbundle/extra/ExtraFieldsFormatter.py
loggerbundle/extra/ExtraKeysResolver.py
loggerbundle/handler/HandlerFactoryInterface.py
loggerbundle/stdout/StreamHandlerFactory.py
logger_bundle-0.7.0.dist-info/entry_points.txt
logger_bundle-0.7.0.dist-info/WHEEL
logger_bundle-0.7.0.dist-info/METADATA
logger_bundle-0.7.0.dist-info/RECORD
